ayu/__init__.py
ayu/__main__.py
ayu/app.py
ayu/command_builder.py
ayu/constants.py
ayu/event_dispatcher.py
ayu/plugin.py
ayu/plugin_list_fetcher.py
ayu/utils.py
ayu/assets/ayu.tcss
ayu/classes/event.py
ayu/widgets/coverage_explorer.py
ayu/widgets/detail_viewer.py
ayu/widgets/filter.py
ayu/widgets/helper_widgets.py
ayu/widgets/log.py
ayu/widgets/navigation.py
ayu/widgets/result_viewer.py
ayu/widgets/modals/plugin_manager.py
ayu/widgets/modals/search.py
ayu-0.4.3.dist-info/METADATA
ayu-0.4.3.dist-info/WHEEL
ayu-0.4.3.dist-info/entry_points.txt
ayu-0.4.3.dist-info/RECORD
