Metadata-Version: 2.4
Name: ayu
Version: 0.4.3
Summary: An interactive TUI for pytest
Project-URL: Repository, https://github.com/Zaloog/ayu
Project-URL: Changelog, https://github.com/Zaloog/ayu/blob/main/CHANGELOG.md
Author-email: Zaloog <gramslars@gmail.com>
Keywords: pytest,python,textual,tui
Classifier: Development Status :: 3 - Alpha
Classifier: License :: OSI Approved :: MIT License
Classifier: Operating System :: OS Independent
Classifier: Programming Language :: Python
Classifier: Programming Language :: Python :: 3 :: Only
Classifier: Programming Language :: Python :: 3.10
Classifier: Programming Language :: Python :: 3.11
Classifier: Programming Language :: Python :: 3.12
Classifier: Programming Language :: Python :: 3.13
Requires-Python: >=3.10
Requires-Dist: click>=8.1.8
Requires-Dist: pytest>=8.3.5
Requires-Dist: requests-cache>=1.2.1
Requires-Dist: textual-slidecontainer>=0.2.5
Requires-Dist: textual-tags>=0.1.0
Requires-Dist: textual[syntax]>=5.2.0
Requires-Dist: watchfiles>=1.0.5
Requires-Dist: websockets>=15.0.1
